nonebot_plugin_osugreek/__init__.py
nonebot_plugin_osugreek/config.py
nonebot_plugin_osugreek/handler.py
nonebot_plugin_osugreek/images/alpha.png
nonebot_plugin_osugreek/images/beta.png
nonebot_plugin_osugreek/images/delta.png
nonebot_plugin_osugreek/images/epsilon.png
nonebot_plugin_osugreek/images/gamma.png
nonebot_plugin_osugreek-1.0.9.dist-info/licenses/License
nonebot_plugin_osugreek-1.0.9.dist-info/METADATA
nonebot_plugin_osugreek-1.0.9.dist-info/WHEEL
nonebot_plugin_osugreek-1.0.9.dist-info/entry_points.txt
nonebot_plugin_osugreek-1.0.9.dist-info/top_level.txt
nonebot_plugin_osugreek-1.0.9.dist-info/RECORD
