Metadata-Version: 2.4
Name: nonebot-plugin-osugreek
Version: 1.0.9
Summary: 在图片中央贴上神秘4k希腊字母并添加色散效果的 NoneBot2 插件
License-Expression: MIT
Project-URL: Homepage, https://github.com/YakumoZn/nonebot-plugin-osugreek
Requires-Python: >=3.8
License-File: License
Requires-Dist: nonebot2>=2.3.0
Requires-Dist: nonebot-adapter-onebot>=2.0.0
Requires-Dist: pillow>=9.0.0
Requires-Dist: aiohttp>=3.8.0
Requires-Dist: nonebot-plugin-localstore>=0.3.0
Dynamic: license-file
